DESCRIPTION.rst
LICENSE
MANIFEST.in
README.md
setup.py
django_quilljs.egg-info/PKG-INFO
django_quilljs.egg-info/SOURCES.txt
django_quilljs.egg-info/dependency_links.txt
django_quilljs.egg-info/not-zip-safe
django_quilljs.egg-info/top_level.txt
quilljs/__init__.py
quilljs/admin.py
quilljs/apps.py
quilljs/fields.py
quilljs/helpers.py
quilljs/widgets.py
quilljs/migrations/__init__.py
quilljs/migrations/__pycache__/__init__.cpython-36.pyc
quilljs/static/.DS_Store
quilljs/static/quilljs/.DS_Store
quilljs/static/quilljs/css/.DS_Store
quilljs/static/quilljs/css/quilljs.core.css
quilljs/static/quilljs/css/quilljs.css
quilljs/static/quilljs/css/quilljs.snow.css
quilljs/static/quilljs/css/quilljs.snow.min.css
quilljs/static/quilljs/css/quilljs.snow.min.css.map
quilljs/static/quilljs/css/vendor/quilljs-0.19.11.snow.css
quilljs/static/quilljs/js/.DS_Store
quilljs/static/quilljs/js/helpers.js
quilljs/static/quilljs/js/image.js
quilljs/static/quilljs/js/quill-django.js
quilljs/static/quilljs/js/build/.gitkeep
quilljs/static/quilljs/js/build/quill-django.min.js
quilljs/static/quilljs/js/build/quilljs-django.js
quilljs/static/quilljs/js/build/quilljs-django.min.js
quilljs/static/quilljs/js/test/helpers.js
quilljs/static/quilljs/js/test/quill-django.js
quilljs/static/quilljs/js/vendor/SimpleAjaxUploader-1a6f62289d.min.js
quilljs/templates/quill/editor.html
quilljs/templates/quill/widget.html
quilljs/templates/quill/toolbars/basic.html
quilljs/templates/quill/toolbars/full.html
quilljs/templatetags/__init__.py
quilljs/templatetags/quilljs_tags.py
quilljs/templatetags/__pycache__/__init__.cpython-36.pyc
quilljs/templatetags/__pycache__/quill_tags.cpython-36.pyc
quilljs/templatetags/__pycache__/quilljs_tags.cpython-36.pyc