Metadata-Version: 1.1
Name: django-quilljs
Version: 0.0.2
Summary: Easily use Quill.js in your django admin.
Home-page: UNKNOWN
Author: Mukesh Yadav
Author-email: mak.gnu@gmail.com
License: UNKNOWN
Platform: any
Classifier: Development Status :: 4 - Beta
Classifier: Environment :: Web Environment
Classifier: Framework :: Django
Classifier: Intended Audience :: Developers
Classifier: License :: OSI Approved :: BSD License
Classifier: Operating System :: OS Independent
Classifier: Programming Language :: Python
Classifier: Programming Language :: Python :: 3
Classifier: Topic :: Internet :: WWW/HTTP :: Browsers
Classifier: Topic :: Internet :: WWW/HTTP :: Site Management
Classifier: Topic :: Office/Business :: Office Suites
Classifier: Topic :: Software Development :: Libraries :: Python Modules
Classifier: Topic :: Software Development :: User Interfaces
Classifier: Topic :: Text Editors :: Word Processors
Classifier: Topic :: Text Processing :: Fonts
Classifier: Topic :: Text Processing :: Markup :: HTML
